Metadata-Version: 2.1
Name: dbam
Version: 0.0.2
Summary: databamboo cli tools
Home-page: https://github.com/databamboo/dbam
Author: Harry Wang
Author-email: support@databamboo.com
License: MIT
Platform: UNKNOWN
Classifier: License :: OSI Approved :: MIT License
Classifier: Programming Language :: Python
Classifier: Programming Language :: Python :: 3
